ImportFromBitbucket.py
setup.py
ImportFromBitbucket.egg-info/PKG-INFO
ImportFromBitbucket.egg-info/SOURCES.txt
ImportFromBitbucket.egg-info/dependency_links.txt
ImportFromBitbucket.egg-info/top_level.txt