Metadata-Version: 1.0
Name: ImportFromBitbucket
Version: 0.1.5
Summary: Import .py files from CommmutativeMonoids project
Home-page: https://bitbucket.org/juan_ignacio_garcia_garcia/commutativemonoids
Author: J. I. García-García
Author-email: ignacio.garcia@uca.es
License: GPL
Platform: UNKNOWN
